{"Type":"memory","Name":"MemoryUsedPercent","Dimension":"","Value":6.38,"NodeId":"algo-1","Timestamp":1682750984.501492}
{"Type":"memory","Name":"MemoryUsedPercent","Dimension":"","Value":6.70,"NodeId":"algo-1","Timestamp":1682750985.000768}
{"Type":"cpu","Name":"cpu3","Dimension":"I/OWaitPercentage","Value":10.42,"NodeId":"algo-1","Timestamp":1682750985.000862}
{"Type":"cpu","Name":"cpu0","Dimension":"I/OWaitPercentage","Value":4.17,"NodeId":"algo-1","Timestamp":1682750985.000862}
{"Type":"cpu","Name":"cpu1","Dimension":"CPUUtilization","Value":89.80,"NodeId":"algo-1","Timestamp":1682750985.000862}
{"Type":"cpu","Name":"cpu1","Dimension":"I/OWaitPercentage","Value":8.16,"NodeId":"algo-1","Timestamp":1682750985.000862}
{"Type":"cpu","Name":"cpu2","Dimension":"CPUUtilization","Value":93.88,"NodeId":"algo-1","Timestamp":1682750985.000862}
{"Type":"cpu","Name":"cpu2","Dimension":"I/OWaitPercentage","Value":2.04,"NodeId":"algo-1","Timestamp":1682750985.000862}
{"Type":"cpu","Name":"cpu0","Dimension":"CPUUtilization","Value":89.58,"NodeId":"algo-1","Timestamp":1682750985.000862}
{"Type":"cpu","Name":"cpu3","Dimension":"CPUUtilization","Value":93.75,"NodeId":"algo-1","Timestamp":1682750985.000862}
{"Type":"i/o","Name":"IOPS","Dimension":"","Value":79.93,"NodeId":"algo-1","Timestamp":1682750985.000964}
{"Type":"i/o","Name":"ReadThroughputInBytesPerSecond","Dimension":"","Value":0.00,"NodeId":"algo-1","Timestamp":1682750985.000964}
{"Type":"i/o","Name":"WriteThroughputInBytesPerSecond","Dimension":"","Value":20954443.92,"NodeId":"algo-1","Timestamp":1682750985.000964}
{"Type":"network","Name":"ReceiveBytesPerSecond","Dimension":"Algorithm","Value":0.00,"NodeId":"algo-1","Timestamp":1682750985.005471}
{"Type":"network","Name":"TransmitBytesPerSecond","Dimension":"Algorithm","Value":0.00,"NodeId":"algo-1","Timestamp":1682750985.005471}
{"Type":"network","Name":"TransmitBytesPerSecond","Dimension":"Platform","Value":506155.97,"NodeId":"algo-1","Timestamp":1682750985.005471}
{"Type":"network","Name":"ReceiveBytesPerSecond","Dimension":"Platform","Value":110062698.12,"NodeId":"algo-1","Timestamp":1682750985.005471}
{"Type":"memory","Name":"MemoryUsedPercent","Dimension":"","Value":7.19,"NodeId":"algo-1","Timestamp":1682750985.500508}
{"Type":"cpu","Name":"cpu0","Dimension":"CPUUtilization","Value":88.24,"NodeId":"algo-1","Timestamp":1682750985.500593}
{"Type":"cpu","Name":"cpu0","Dimension":"I/OWaitPercentage","Value":7.84,"NodeId":"algo-1","Timestamp":1682750985.500593}
{"Type":"cpu","Name":"cpu1","Dimension":"CPUUtilization","Value":87.50,"NodeId":"algo-1","Timestamp":1682750985.500593}
{"Type":"cpu","Name":"cpu1","Dimension":"I/OWaitPercentage","Value":8.33,"NodeId":"algo-1","Timestamp":1682750985.500593}
{"Type":"cpu","Name":"cpu2","Dimension":"CPUUtilization","Value":93.88,"NodeId":"algo-1","Timestamp":1682750985.500593}
{"Type":"cpu","Name":"cpu2","Dimension":"I/OWaitPercentage","Value":2.04,"NodeId":"algo-1","Timestamp":1682750985.500593}
{"Type":"cpu","Name":"cpu3","Dimension":"CPUUtilization","Value":95.74,"NodeId":"algo-1","Timestamp":1682750985.500593}
{"Type":"cpu","Name":"cpu3","Dimension":"I/OWaitPercentage","Value":14.89,"NodeId":"algo-1","Timestamp":1682750985.500593}
{"Type":"i/o","Name":"IOPS","Dimension":"","Value":4492.60,"NodeId":"algo-1","Timestamp":1682750985.500675}
{"Type":"i/o","Name":"ReadThroughputInBytesPerSecond","Dimension":"","Value":9034857.79,"NodeId":"algo-1","Timestamp":1682750985.500675}
{"Type":"i/o","Name":"WriteThroughputInBytesPerSecond","Dimension":"","Value":1054723847.94,"NodeId":"algo-1","Timestamp":1682750985.500675}
{"Type":"network","Name":"TransmitBytesPerSecond","Dimension":"Platform","Value":419588.47,"NodeId":"algo-1","Timestamp":1682750985.505876}
{"Type":"network","Name":"ReceiveBytesPerSecond","Dimension":"Algorithm","Value":0.00,"NodeId":"algo-1","Timestamp":1682750985.505876}
{"Type":"network","Name":"ReceiveBytesPerSecond","Dimension":"Platform","Value":109790790.10,"NodeId":"algo-1","Timestamp":1682750985.505876}
{"Type":"network","Name":"TransmitBytesPerSecond","Dimension":"Algorithm","Value":0.00,"NodeId":"algo-1","Timestamp":1682750985.505876}
{"Type":"memory","Name":"MemoryUsedPercent","Dimension":"","Value":7.36,"NodeId":"algo-1","Timestamp":1682750986.000501}
{"Type":"cpu","Name":"cpu0","Dimension":"CPUUtilization","Value":89.80,"NodeId":"algo-1","Timestamp":1682750986.000566}
{"Type":"cpu","Name":"cpu0","Dimension":"I/OWaitPercentage","Value":10.20,"NodeId":"algo-1","Timestamp":1682750986.000566}
{"Type":"cpu","Name":"cpu1","Dimension":"CPUUtilization","Value":91.30,"NodeId":"algo-1","Timestamp":1682750986.000566}
{"Type":"cpu","Name":"cpu1","Dimension":"I/OWaitPercentage","Value":10.87,"NodeId":"algo-1","Timestamp":1682750986.000566}
{"Type":"cpu","Name":"cpu2","Dimension":"CPUUtilization","Value":93.88,"NodeId":"algo-1","Timestamp":1682750986.000566}
{"Type":"cpu","Name":"cpu2","Dimension":"I/OWaitPercentage","Value":0.00,"NodeId":"algo-1","Timestamp":1682750986.000566}
{"Type":"cpu","Name":"cpu3","Dimension":"CPUUtilization","Value":95.56,"NodeId":"algo-1","Timestamp":1682750986.000566}
{"Type":"cpu","Name":"cpu3","Dimension":"I/OWaitPercentage","Value":17.78,"NodeId":"algo-1","Timestamp":1682750986.000566}
{"Type":"i/o","Name":"IOPS","Dimension":"","Value":160.01,"NodeId":"algo-1","Timestamp":1682750986.000654}
{"Type":"i/o","Name":"ReadThroughputInBytesPerSecond","Dimension":"","Value":0.00,"NodeId":"algo-1","Timestamp":1682750986.000654}
{"Type":"i/o","Name":"WriteThroughputInBytesPerSecond","Dimension":"","Value":41936587.73,"NodeId":"algo-1","Timestamp":1682750986.000654}
{"Type":"network","Name":"TransmitBytesPerSecond","Dimension":"Platform","Value":382317.32,"NodeId":"algo-1","Timestamp":1682750986.006212}
{"Type":"network","Name":"ReceiveBytesPerSecond","Dimension":"Algorithm","Value":0.00,"NodeId":"algo-1","Timestamp":1682750986.006212}
{"Type":"network","Name":"ReceiveBytesPerSecond","Dimension":"Platform","Value":109775885.93,"NodeId":"algo-1","Timestamp":1682750986.006212}
{"Type":"network","Name":"TransmitBytesPerSecond","Dimension":"Algorithm","Value":0.00,"NodeId":"algo-1","Timestamp":1682750986.006212}
{"Type":"i/o","Name":"IOPS","Dimension":"","Value":4565.18,"NodeId":"algo-1","Timestamp":1682750986.501183}
{"Type":"i/o","Name":"ReadThroughputInBytesPerSecond","Dimension":"","Value":9020100.72,"NodeId":"algo-1","Timestamp":1682750986.501183}
{"Type":"i/o","Name":"WriteThroughputInBytesPerSecond","Dimension":"","Value":1073950499.50,"NodeId":"algo-1","Timestamp":1682750986.501183}
{"Type":"cpu","Name":"cpu0","Dimension":"CPUUtilization","Value":88.00,"NodeId":"algo-1","Timestamp":1682750986.501197}
{"Type":"cpu","Name":"cpu0","Dimension":"I/OWaitPercentage","Value":12.00,"NodeId":"algo-1","Timestamp":1682750986.501197}
{"Type":"cpu","Name":"cpu1","Dimension":"I/OWaitPercentage","Value":16.00,"NodeId":"algo-1","Timestamp":1682750986.501197}
{"Type":"cpu","Name":"cpu2","Dimension":"CPUUtilization","Value":91.67,"NodeId":"algo-1","Timestamp":1682750986.501197}
{"Type":"cpu","Name":"cpu2","Dimension":"I/OWaitPercentage","Value":6.25,"NodeId":"algo-1","Timestamp":1682750986.501197}
{"Type":"cpu","Name":"cpu3","Dimension":"CPUUtilization","Value":92.16,"NodeId":"algo-1","Timestamp":1682750986.501197}
{"Type":"cpu","Name":"cpu3","Dimension":"I/OWaitPercentage","Value":11.76,"NodeId":"algo-1","Timestamp":1682750986.501197}
{"Type":"cpu","Name":"cpu1","Dimension":"CPUUtilization","Value":90.00,"NodeId":"algo-1","Timestamp":1682750986.501197}
{"Type":"memory","Name":"MemoryUsedPercent","Dimension":"","Value":7.23,"NodeId":"algo-1","Timestamp":1682750986.501343}
{"Type":"network","Name":"ReceiveBytesPerSecond","Dimension":"Algorithm","Value":0.00,"NodeId":"algo-1","Timestamp":1682750986.505238}
{"Type":"network","Name":"TransmitBytesPerSecond","Dimension":"Algorithm","Value":0.00,"NodeId":"algo-1","Timestamp":1682750986.505238}
{"Type":"network","Name":"ReceiveBytesPerSecond","Dimension":"Platform","Value":110038544.92,"NodeId":"algo-1","Timestamp":1682750986.505238}
{"Type":"network","Name":"TransmitBytesPerSecond","Dimension":"Platform","Value":353740.71,"NodeId":"algo-1","Timestamp":1682750986.505238}
{"Type":"memory","Name":"MemoryUsedPercent","Dimension":"","Value":7.67,"NodeId":"algo-1","Timestamp":1682750987.000545}
{"Type":"cpu","Name":"cpu1","Dimension":"CPUUtilization","Value":71.74,"NodeId":"algo-1","Timestamp":1682750987.000621}
{"Type":"cpu","Name":"cpu0","Dimension":"I/OWaitPercentage","Value":9.80,"NodeId":"algo-1","Timestamp":1682750987.000621}
{"Type":"cpu","Name":"cpu0","Dimension":"CPUUtilization","Value":86.27,"NodeId":"algo-1","Timestamp":1682750987.000621}
{"Type":"cpu","Name":"cpu1","Dimension":"I/OWaitPercentage","Value":6.52,"NodeId":"algo-1","Timestamp":1682750987.000621}
{"Type":"cpu","Name":"cpu2","Dimension":"CPUUtilization","Value":88.46,"NodeId":"algo-1","Timestamp":1682750987.000621}
{"Type":"cpu","Name":"cpu2","Dimension":"I/OWaitPercentage","Value":5.77,"NodeId":"algo-1","Timestamp":1682750987.000621}
{"Type":"cpu","Name":"cpu3","Dimension":"CPUUtilization","Value":82.61,"NodeId":"algo-1","Timestamp":1682750987.000621}
{"Type":"cpu","Name":"cpu3","Dimension":"I/OWaitPercentage","Value":19.57,"NodeId":"algo-1","Timestamp":1682750987.000621}
{"Type":"i/o","Name":"IOPS","Dimension":"","Value":240.20,"NodeId":"algo-1","Timestamp":1682750987.000762}
{"Type":"i/o","Name":"ReadThroughputInBytesPerSecond","Dimension":"","Value":0.00,"NodeId":"algo-1","Timestamp":1682750987.000762}
{"Type":"i/o","Name":"WriteThroughputInBytesPerSecond","Dimension":"","Value":62959385.75,"NodeId":"algo-1","Timestamp":1682750987.000762}
{"Type":"network","Name":"ReceiveBytesPerSecond","Dimension":"Algorithm","Value":0.00,"NodeId":"algo-1","Timestamp":1682750987.008599}
{"Type":"network","Name":"TransmitBytesPerSecond","Dimension":"Algorithm","Value":0.00,"NodeId":"algo-1","Timestamp":1682750987.008599}
{"Type":"network","Name":"ReceiveBytesPerSecond","Dimension":"Platform","Value":102669546.99,"NodeId":"algo-1","Timestamp":1682750987.008599}
{"Type":"network","Name":"TransmitBytesPerSecond","Dimension":"Platform","Value":335600.26,"NodeId":"algo-1","Timestamp":1682750987.008599}
{"Type":"memory","Name":"MemoryUsedPercent","Dimension":"","Value":7.95,"NodeId":"algo-1","Timestamp":1682750987.501308}
{"Type":"cpu","Name":"cpu1","Dimension":"CPUUtilization","Value":96.00,"NodeId":"algo-1","Timestamp":1682750987.501409}
{"Type":"cpu","Name":"cpu0","Dimension":"I/OWaitPercentage","Value":6.12,"NodeId":"algo-1","Timestamp":1682750987.501409}
{"Type":"cpu","Name":"cpu0","Dimension":"CPUUtilization","Value":93.88,"NodeId":"algo-1","Timestamp":1682750987.501409}
{"Type":"cpu","Name":"cpu1","Dimension":"I/OWaitPercentage","Value":12.00,"NodeId":"algo-1","Timestamp":1682750987.501409}
{"Type":"cpu","Name":"cpu2","Dimension":"CPUUtilization","Value":95.92,"NodeId":"algo-1","Timestamp":1682750987.501409}
{"Type":"cpu","Name":"cpu2","Dimension":"I/OWaitPercentage","Value":2.04,"NodeId":"algo-1","Timestamp":1682750987.501409}
{"Type":"cpu","Name":"cpu3","Dimension":"CPUUtilization","Value":100.00,"NodeId":"algo-1","Timestamp":1682750987.501409}
{"Type":"cpu","Name":"cpu3","Dimension":"I/OWaitPercentage","Value":8.16,"NodeId":"algo-1","Timestamp":1682750987.501409}
{"Type":"i/o","Name":"IOPS","Dimension":"","Value":4655.15,"NodeId":"algo-1","Timestamp":1682750987.501497}
{"Type":"i/o","Name":"WriteThroughputInBytesPerSecond","Dimension":"","Value":1097587438.71,"NodeId":"algo-1","Timestamp":1682750987.501497}
{"Type":"i/o","Name":"ReadThroughputInBytesPerSecond","Dimension":"","Value":9016364.24,"NodeId":"algo-1","Timestamp":1682750987.501497}
{"Type":"network","Name":"ReceiveBytesPerSecond","Dimension":"Algorithm","Value":0.00,"NodeId":"algo-1","Timestamp":1682750987.526381}
{"Type":"network","Name":"TransmitBytesPerSecond","Dimension":"Algorithm","Value":0.00,"NodeId":"algo-1","Timestamp":1682750987.526381}
{"Type":"network","Name":"ReceiveBytesPerSecond","Dimension":"Platform","Value":100130442.62,"NodeId":"algo-1","Timestamp":1682750987.526381}
{"Type":"network","Name":"TransmitBytesPerSecond","Dimension":"Platform","Value":164385.72,"NodeId":"algo-1","Timestamp":1682750987.526381}
{"Type":"memory","Name":"MemoryUsedPercent","Dimension":"","Value":7.98,"NodeId":"algo-1","Timestamp":1682750988.001251}
{"Type":"cpu","Name":"cpu1","Dimension":"CPUUtilization","Value":97.87,"NodeId":"algo-1","Timestamp":1682750988.001366}
{"Type":"cpu","Name":"cpu0","Dimension":"I/OWaitPercentage","Value":7.84,"NodeId":"algo-1","Timestamp":1682750988.001366}
{"Type":"cpu","Name":"cpu0","Dimension":"CPUUtilization","Value":94.12,"NodeId":"algo-1","Timestamp":1682750988.001366}
{"Type":"cpu","Name":"cpu1","Dimension":"I/OWaitPercentage","Value":14.89,"NodeId":"algo-1","Timestamp":1682750988.001366}
{"Type":"cpu","Name":"cpu2","Dimension":"CPUUtilization","Value":100.00,"NodeId":"algo-1","Timestamp":1682750988.001366}
{"Type":"cpu","Name":"cpu2","Dimension":"I/OWaitPercentage","Value":1.96,"NodeId":"algo-1","Timestamp":1682750988.001366}
{"Type":"cpu","Name":"cpu3","Dimension":"CPUUtilization","Value":97.78,"NodeId":"algo-1","Timestamp":1682750988.001366}
{"Type":"cpu","Name":"cpu3","Dimension":"I/OWaitPercentage","Value":17.78,"NodeId":"algo-1","Timestamp":1682750988.001366}
{"Type":"i/o","Name":"WriteThroughputInBytesPerSecond","Dimension":"","Value":80812631.53,"NodeId":"algo-1","Timestamp":1682750988.001456}
{"Type":"i/o","Name":"ReadThroughputInBytesPerSecond","Dimension":"","Value":0.00,"NodeId":"algo-1","Timestamp":1682750988.001456}
{"Type":"i/o","Name":"IOPS","Dimension":"","Value":312.03,"NodeId":"algo-1","Timestamp":1682750988.001456}
{"Type":"network","Name":"ReceiveBytesPerSecond","Dimension":"Algorithm","Value":0.00,"NodeId":"algo-1","Timestamp":1682750988.006401}
{"Type":"network","Name":"TransmitBytesPerSecond","Dimension":"Algorithm","Value":0.00,"NodeId":"algo-1","Timestamp":1682750988.006401}
{"Type":"network","Name":"ReceiveBytesPerSecond","Dimension":"Platform","Value":96858063.25,"NodeId":"algo-1","Timestamp":1682750988.006401}
{"Type":"network","Name":"TransmitBytesPerSecond","Dimension":"Platform","Value":140481.63,"NodeId":"algo-1","Timestamp":1682750988.006401}
{"Type":"memory","Name":"MemoryUsedPercent","Dimension":"","Value":8.28,"NodeId":"algo-1","Timestamp":1682750988.501247}
{"Type":"cpu","Name":"cpu3","Dimension":"I/OWaitPercentage","Value":3.85,"NodeId":"algo-1","Timestamp":1682750988.501370}
{"Type":"cpu","Name":"cpu0","Dimension":"I/OWaitPercentage","Value":3.85,"NodeId":"algo-1","Timestamp":1682750988.501370}
{"Type":"cpu","Name":"cpu1","Dimension":"CPUUtilization","Value":90.00,"NodeId":"algo-1","Timestamp":1682750988.501370}
{"Type":"cpu","Name":"cpu1","Dimension":"I/OWaitPercentage","Value":8.00,"NodeId":"algo-1","Timestamp":1682750988.501370}
{"Type":"cpu","Name":"cpu2","Dimension":"CPUUtilization","Value":90.20,"NodeId":"algo-1","Timestamp":1682750988.501370}
{"Type":"cpu","Name":"cpu2","Dimension":"I/OWaitPercentage","Value":7.84,"NodeId":"algo-1","Timestamp":1682750988.501370}
{"Type":"cpu","Name":"cpu0","Dimension":"CPUUtilization","Value":96.15,"NodeId":"algo-1","Timestamp":1682750988.501370}
{"Type":"cpu","Name":"cpu3","Dimension":"CPUUtilization","Value":96.15,"NodeId":"algo-1","Timestamp":1682750988.501370}
{"Type":"i/o","Name":"IOPS","Dimension":"","Value":4738.20,"NodeId":"algo-1","Timestamp":1682750988.501857}
{"Type":"i/o","Name":"ReadThroughputInBytesPerSecond","Dimension":"","Value":9022387.08,"NodeId":"algo-1","Timestamp":1682750988.501857}
{"Type":"i/o","Name":"WriteThroughputInBytesPerSecond","Dimension":"","Value":1119275308.90,"NodeId":"algo-1","Timestamp":1682750988.501857}
{"Type":"network","Name":"ReceiveBytesPerSecond","Dimension":"Algorithm","Value":0.00,"NodeId":"algo-1","Timestamp":1682750988.510755}
{"Type":"network","Name":"TransmitBytesPerSecond","Dimension":"Algorithm","Value":0.00,"NodeId":"algo-1","Timestamp":1682750988.510755}
{"Type":"network","Name":"ReceiveBytesPerSecond","Dimension":"Platform","Value":87252430.63,"NodeId":"algo-1","Timestamp":1682750988.510755}
{"Type":"network","Name":"TransmitBytesPerSecond","Dimension":"Platform","Value":109304.33,"NodeId":"algo-1","Timestamp":1682750988.510755}
{"Type":"memory","Name":"MemoryUsedPercent","Dimension":"","Value":9.16,"NodeId":"algo-1","Timestamp":1682750989.001178}
{"Type":"cpu","Name":"cpu0","Dimension":"CPUUtilization","Value":100.00,"NodeId":"algo-1","Timestamp":1682750989.001239}
{"Type":"cpu","Name":"cpu0","Dimension":"I/OWaitPercentage","Value":4.17,"NodeId":"algo-1","Timestamp":1682750989.001239}
{"Type":"cpu","Name":"cpu1","Dimension":"CPUUtilization","Value":100.00,"NodeId":"algo-1","Timestamp":1682750989.001239}
{"Type":"cpu","Name":"cpu1","Dimension":"I/OWaitPercentage","Value":20.83,"NodeId":"algo-1","Timestamp":1682750989.001239}
{"Type":"cpu","Name":"cpu2","Dimension":"CPUUtilization","Value":89.80,"NodeId":"algo-1","Timestamp":1682750989.001239}
{"Type":"cpu","Name":"cpu2","Dimension":"I/OWaitPercentage","Value":2.04,"NodeId":"algo-1","Timestamp":1682750989.001239}
{"Type":"cpu","Name":"cpu3","Dimension":"CPUUtilization","Value":100.00,"NodeId":"algo-1","Timestamp":1682750989.001239}
{"Type":"cpu","Name":"cpu3","Dimension":"I/OWaitPercentage","Value":18.75,"NodeId":"algo-1","Timestamp":1682750989.001239}
{"Type":"i/o","Name":"IOPS","Dimension":"","Value":392.40,"NodeId":"algo-1","Timestamp":1682750989.001342}
{"Type":"i/o","Name":"ReadThroughputInBytesPerSecond","Dimension":"","Value":0.00,"NodeId":"algo-1","Timestamp":1682750989.001342}
{"Type":"i/o","Name":"WriteThroughputInBytesPerSecond","Dimension":"","Value":101874240.39,"NodeId":"algo-1","Timestamp":1682750989.001342}
{"Type":"network","Name":"ReceiveBytesPerSecond","Dimension":"Algorithm","Value":0.00,"NodeId":"algo-1","Timestamp":1682750989.010013}
{"Type":"network","Name":"TransmitBytesPerSecond","Dimension":"Algorithm","Value":0.00,"NodeId":"algo-1","Timestamp":1682750989.010013}
{"Type":"network","Name":"ReceiveBytesPerSecond","Dimension":"Platform","Value":110433442.09,"NodeId":"algo-1","Timestamp":1682750989.010013}
{"Type":"network","Name":"TransmitBytesPerSecond","Dimension":"Platform","Value":180531.89,"NodeId":"algo-1","Timestamp":1682750989.010013}
{"Type":"memory","Name":"MemoryUsedPercent","Dimension":"","Value":9.42,"NodeId":"algo-1","Timestamp":1682750989.500588}
{"Type":"cpu","Name":"cpu0","Dimension":"CPUUtilization","Value":91.67,"NodeId":"algo-1","Timestamp":1682750989.500669}
{"Type":"cpu","Name":"cpu0","Dimension":"I/OWaitPercentage","Value":16.67,"NodeId":"algo-1","Timestamp":1682750989.500669}
{"Type":"cpu","Name":"cpu1","Dimension":"CPUUtilization","Value":93.62,"NodeId":"algo-1","Timestamp":1682750989.500669}
{"Type":"cpu","Name":"cpu1","Dimension":"I/OWaitPercentage","Value":14.89,"NodeId":"algo-1","Timestamp":1682750989.500669}
{"Type":"cpu","Name":"cpu2","Dimension":"CPUUtilization","Value":98.00,"NodeId":"algo-1","Timestamp":1682750989.500669}
{"Type":"cpu","Name":"cpu2","Dimension":"I/OWaitPercentage","Value":4.00,"NodeId":"algo-1","Timestamp":1682750989.500669}
{"Type":"cpu","Name":"cpu3","Dimension":"CPUUtilization","Value":100.00,"NodeId":"algo-1","Timestamp":1682750989.500669}
{"Type":"cpu","Name":"cpu3","Dimension":"I/OWaitPercentage","Value":20.83,"NodeId":"algo-1","Timestamp":1682750989.500669}
{"Type":"i/o","Name":"IOPS","Dimension":"","Value":4815.56,"NodeId":"algo-1","Timestamp":1682750989.500764}
{"Type":"i/o","Name":"ReadThroughputInBytesPerSecond","Dimension":"","Value":9040068.06,"NodeId":"algo-1","Timestamp":1682750989.500764}
{"Type":"i/o","Name":"WriteThroughputInBytesPerSecond","Dimension":"","Value":1139315123.31,"NodeId":"algo-1","Timestamp":1682750989.500764}
{"Type":"network","Name":"ReceiveBytesPerSecond","Dimension":"Algorithm","Value":0.00,"NodeId":"algo-1","Timestamp":1682750989.504613}
{"Type":"network","Name":"TransmitBytesPerSecond","Dimension":"Algorithm","Value":0.00,"NodeId":"algo-1","Timestamp":1682750989.504613}
{"Type":"network","Name":"ReceiveBytesPerSecond","Dimension":"Platform","Value":111044959.82,"NodeId":"algo-1","Timestamp":1682750989.504613}
{"Type":"network","Name":"TransmitBytesPerSecond","Dimension":"Platform","Value":533339.75,"NodeId":"algo-1","Timestamp":1682750989.504613}
{"Type":"memory","Name":"MemoryUsedPercent","Dimension":"","Value":9.72,"NodeId":"algo-1","Timestamp":1682750990.001225}
{"Type":"cpu","Name":"cpu0","Dimension":"CPUUtilization","Value":95.83,"NodeId":"algo-1","Timestamp":1682750990.001306}
{"Type":"cpu","Name":"cpu0","Dimension":"I/OWaitPercentage","Value":27.08,"NodeId":"algo-1","Timestamp":1682750990.001306}
{"Type":"cpu","Name":"cpu1","Dimension":"CPUUtilization","Value":95.92,"NodeId":"algo-1","Timestamp":1682750990.001306}
{"Type":"cpu","Name":"cpu1","Dimension":"I/OWaitPercentage","Value":18.37,"NodeId":"algo-1","Timestamp":1682750990.001306}
{"Type":"cpu","Name":"cpu2","Dimension":"CPUUtilization","Value":95.92,"NodeId":"algo-1","Timestamp":1682750990.001306}
{"Type":"cpu","Name":"cpu2","Dimension":"I/OWaitPercentage","Value":10.20,"NodeId":"algo-1","Timestamp":1682750990.001306}
{"Type":"cpu","Name":"cpu3","Dimension":"CPUUtilization","Value":95.83,"NodeId":"algo-1","Timestamp":1682750990.001306}
{"Type":"cpu","Name":"cpu3","Dimension":"I/OWaitPercentage","Value":16.67,"NodeId":"algo-1","Timestamp":1682750990.001306}
{"Type":"i/o","Name":"IOPS","Dimension":"","Value":451.44,"NodeId":"algo-1","Timestamp":1682750990.001385}
{"Type":"i/o","Name":"ReadThroughputInBytesPerSecond","Dimension":"","Value":0.00,"NodeId":"algo-1","Timestamp":1682750990.001385}
{"Type":"i/o","Name":"WriteThroughputInBytesPerSecond","Dimension":"","Value":117352197.62,"NodeId":"algo-1","Timestamp":1682750990.001385}
{"Type":"network","Name":"ReceiveBytesPerSecond","Dimension":"Algorithm","Value":0.00,"NodeId":"algo-1","Timestamp":1682750990.016508}
{"Type":"network","Name":"TransmitBytesPerSecond","Dimension":"Algorithm","Value":0.00,"NodeId":"algo-1","Timestamp":1682750990.016508}
{"Type":"network","Name":"ReceiveBytesPerSecond","Dimension":"Platform","Value":107417649.93,"NodeId":"algo-1","Timestamp":1682750990.016508}
{"Type":"network","Name":"TransmitBytesPerSecond","Dimension":"Platform","Value":708276.52,"NodeId":"algo-1","Timestamp":1682750990.016508}
{"Type":"cpu","Name":"cpu0","Dimension":"CPUUtilization","Value":83.67,"NodeId":"algo-1","Timestamp":1682750990.501404}
{"Type":"cpu","Name":"cpu0","Dimension":"I/OWaitPercentage","Value":10.20,"NodeId":"algo-1","Timestamp":1682750990.501404}
{"Type":"cpu","Name":"cpu1","Dimension":"CPUUtilization","Value":97.87,"NodeId":"algo-1","Timestamp":1682750990.501404}
{"Type":"cpu","Name":"cpu1","Dimension":"I/OWaitPercentage","Value":23.40,"NodeId":"algo-1","Timestamp":1682750990.501404}
{"Type":"cpu","Name":"cpu3","Dimension":"I/OWaitPercentage","Value":22.00,"NodeId":"algo-1","Timestamp":1682750990.501404}
{"Type":"cpu","Name":"cpu2","Dimension":"I/OWaitPercentage","Value":1.96,"NodeId":"algo-1","Timestamp":1682750990.501404}
{"Type":"cpu","Name":"cpu3","Dimension":"CPUUtilization","Value":98.00,"NodeId":"algo-1","Timestamp":1682750990.501404}
{"Type":"cpu","Name":"cpu2","Dimension":"CPUUtilization","Value":98.04,"NodeId":"algo-1","Timestamp":1682750990.501404}
{"Type":"i/o","Name":"IOPS","Dimension":"","Value":4861.77,"NodeId":"algo-1","Timestamp":1682750990.501820}
{"Type":"i/o","Name":"ReadThroughputInBytesPerSecond","Dimension":"","Value":9021776.70,"NodeId":"algo-1","Timestamp":1682750990.501820}
{"Type":"i/o","Name":"WriteThroughputInBytesPerSecond","Dimension":"","Value":1151677165.34,"NodeId":"algo-1","Timestamp":1682750990.501820}
{"Type":"memory","Name":"MemoryUsedPercent","Dimension":"","Value":10.36,"NodeId":"algo-1","Timestamp":1682750990.504834}
{"Type":"network","Name":"ReceiveBytesPerSecond","Dimension":"Algorithm","Value":0.00,"NodeId":"algo-1","Timestamp":1682750990.517172}
{"Type":"network","Name":"TransmitBytesPerSecond","Dimension":"Algorithm","Value":0.00,"NodeId":"algo-1","Timestamp":1682750990.517172}
{"Type":"network","Name":"ReceiveBytesPerSecond","Dimension":"Platform","Value":104054710.23,"NodeId":"algo-1","Timestamp":1682750990.517172}
{"Type":"network","Name":"TransmitBytesPerSecond","Dimension":"Platform","Value":465455.88,"NodeId":"algo-1","Timestamp":1682750990.517172}
{"Type":"memory","Name":"MemoryUsedPercent","Dimension":"","Value":10.71,"NodeId":"algo-1","Timestamp":1682750991.001239}
{"Type":"cpu","Name":"cpu3","Dimension":"I/OWaitPercentage","Value":10.64,"NodeId":"algo-1","Timestamp":1682750991.001319}
{"Type":"cpu","Name":"cpu0","Dimension":"I/OWaitPercentage","Value":16.67,"NodeId":"algo-1","Timestamp":1682750991.001319}
{"Type":"cpu","Name":"cpu1","Dimension":"CPUUtilization","Value":98.00,"NodeId":"algo-1","Timestamp":1682750991.001319}
{"Type":"cpu","Name":"cpu1","Dimension":"I/OWaitPercentage","Value":10.00,"NodeId":"algo-1","Timestamp":1682750991.001319}
{"Type":"cpu","Name":"cpu0","Dimension":"CPUUtilization","Value":95.83,"NodeId":"algo-1","Timestamp":1682750991.001319}
{"Type":"cpu","Name":"cpu2","Dimension":"I/OWaitPercentage","Value":5.88,"NodeId":"algo-1","Timestamp":1682750991.001319}
{"Type":"cpu","Name":"cpu3","Dimension":"CPUUtilization","Value":100.00,"NodeId":"algo-1","Timestamp":1682750991.001319}
{"Type":"cpu","Name":"cpu2","Dimension":"CPUUtilization","Value":96.08,"NodeId":"algo-1","Timestamp":1682750991.001319}
{"Type":"i/o","Name":"IOPS","Dimension":"","Value":508.42,"NodeId":"algo-1","Timestamp":1682750991.001404}
{"Type":"i/o","Name":"ReadThroughputInBytesPerSecond","Dimension":"","Value":0.00,"NodeId":"algo-1","Timestamp":1682750991.001404}
{"Type":"i/o","Name":"WriteThroughputInBytesPerSecond","Dimension":"","Value":132288057.44,"NodeId":"algo-1","Timestamp":1682750991.001404}
{"Type":"network","Name":"ReceiveBytesPerSecond","Dimension":"Algorithm","Value":0.00,"NodeId":"algo-1","Timestamp":1682750991.010140}
{"Type":"network","Name":"TransmitBytesPerSecond","Dimension":"Algorithm","Value":0.00,"NodeId":"algo-1","Timestamp":1682750991.010140}
{"Type":"network","Name":"ReceiveBytesPerSecond","Dimension":"Platform","Value":111315428.76,"NodeId":"algo-1","Timestamp":1682750991.010140}
{"Type":"network","Name":"TransmitBytesPerSecond","Dimension":"Platform","Value":483073.64,"NodeId":"algo-1","Timestamp":1682750991.010140}
{"Type":"memory","Name":"MemoryUsedPercent","Dimension":"","Value":11.04,"NodeId":"algo-1","Timestamp":1682750991.505260}
{"Type":"i/o","Name":"ReadThroughputInBytesPerSecond","Dimension":"","Value":8958863.39,"NodeId":"algo-1","Timestamp":1682750991.505354}
{"Type":"i/o","Name":"IOPS","Dimension":"","Value":4827.86,"NodeId":"algo-1","Timestamp":1682750991.505354}
{"Type":"i/o","Name":"WriteThroughputInBytesPerSecond","Dimension":"","Value":1143645951.42,"NodeId":"algo-1","Timestamp":1682750991.505354}
{"Type":"cpu","Name":"cpu3","Dimension":"I/OWaitPercentage","Value":14.00,"NodeId":"algo-1","Timestamp":1682750991.505440}
{"Type":"cpu","Name":"cpu0","Dimension":"I/OWaitPercentage","Value":23.53,"NodeId":"algo-1","Timestamp":1682750991.505440}
{"Type":"cpu","Name":"cpu1","Dimension":"CPUUtilization","Value":96.15,"NodeId":"algo-1","Timestamp":1682750991.505440}
{"Type":"cpu","Name":"cpu1","Dimension":"I/OWaitPercentage","Value":9.62,"NodeId":"algo-1","Timestamp":1682750991.505440}
{"Type":"cpu","Name":"cpu2","Dimension":"CPUUtilization","Value":97.96,"NodeId":"algo-1","Timestamp":1682750991.505440}
{"Type":"cpu","Name":"cpu2","Dimension":"I/OWaitPercentage","Value":6.12,"NodeId":"algo-1","Timestamp":1682750991.505440}
{"Type":"cpu","Name":"cpu3","Dimension":"CPUUtilization","Value":98.00,"NodeId":"algo-1","Timestamp":1682750991.505440}
{"Type":"cpu","Name":"cpu0","Dimension":"CPUUtilization","Value":98.04,"NodeId":"algo-1","Timestamp":1682750991.505440}
{"Type":"network","Name":"ReceiveBytesPerSecond","Dimension":"Algorithm","Value":0.00,"NodeId":"algo-1","Timestamp":1682750991.512265}
{"Type":"network","Name":"TransmitBytesPerSecond","Dimension":"Algorithm","Value":0.00,"NodeId":"algo-1","Timestamp":1682750991.512265}
{"Type":"network","Name":"ReceiveBytesPerSecond","Dimension":"Platform","Value":110357537.75,"NodeId":"algo-1","Timestamp":1682750991.512265}
{"Type":"network","Name":"TransmitBytesPerSecond","Dimension":"Platform","Value":612886.62,"NodeId":"algo-1","Timestamp":1682750991.512265}
{"Type":"memory","Name":"MemoryUsedPercent","Dimension":"","Value":11.64,"NodeId":"algo-1","Timestamp":1682750992.001224}
{"Type":"cpu","Name":"cpu3","Dimension":"CPUUtilization","Value":97.96,"NodeId":"algo-1","Timestamp":1682750992.001303}
{"Type":"cpu","Name":"cpu0","Dimension":"I/OWaitPercentage","Value":14.00,"NodeId":"algo-1","Timestamp":1682750992.001303}
{"Type":"cpu","Name":"cpu1","Dimension":"CPUUtilization","Value":97.92,"NodeId":"algo-1","Timestamp":1682750992.001303}
{"Type":"cpu","Name":"cpu1","Dimension":"I/OWaitPercentage","Value":10.42,"NodeId":"algo-1","Timestamp":1682750992.001303}
{"Type":"cpu","Name":"cpu2","Dimension":"CPUUtilization","Value":95.74,"NodeId":"algo-1","Timestamp":1682750992.001303}
{"Type":"cpu","Name":"cpu2","Dimension":"I/OWaitPercentage","Value":4.26,"NodeId":"algo-1","Timestamp":1682750992.001303}
{"Type":"cpu","Name":"cpu0","Dimension":"CPUUtilization","Value":90.00,"NodeId":"algo-1","Timestamp":1682750992.001303}
{"Type":"cpu","Name":"cpu3","Dimension":"I/OWaitPercentage","Value":8.16,"NodeId":"algo-1","Timestamp":1682750992.001303}
{"Type":"i/o","Name":"IOPS","Dimension":"","Value":578.60,"NodeId":"algo-1","Timestamp":1682750992.001382}
{"Type":"i/o","Name":"ReadThroughputInBytesPerSecond","Dimension":"","Value":0.00,"NodeId":"algo-1","Timestamp":1682750992.001382}
{"Type":"i/o","Name":"WriteThroughputInBytesPerSecond","Dimension":"","Value":133649051.18,"NodeId":"algo-1","Timestamp":1682750992.001382}
{"Type":"network","Name":"ReceiveBytesPerSecond","Dimension":"Algorithm","Value":0.00,"NodeId":"algo-1","Timestamp":1682750992.006160}
{"Type":"network","Name":"TransmitBytesPerSecond","Dimension":"Algorithm","Value":0.00,"NodeId":"algo-1","Timestamp":1682750992.006160}
{"Type":"network","Name":"ReceiveBytesPerSecond","Dimension":"Platform","Value":110401875.65,"NodeId":"algo-1","Timestamp":1682750992.006160}
{"Type":"network","Name":"TransmitBytesPerSecond","Dimension":"Platform","Value":652112.53,"NodeId":"algo-1","Timestamp":1682750992.006160}
{"Type":"memory","Name":"MemoryUsedPercent","Dimension":"","Value":12.40,"NodeId":"algo-1","Timestamp":1682750992.500535}
{"Type":"cpu","Name":"cpu3","Dimension":"I/OWaitPercentage","Value":2.08,"NodeId":"algo-1","Timestamp":1682750992.500617}
{"Type":"cpu","Name":"cpu0","Dimension":"I/OWaitPercentage","Value":10.64,"NodeId":"algo-1","Timestamp":1682750992.500617}
{"Type":"cpu","Name":"cpu1","Dimension":"CPUUtilization","Value":100.00,"NodeId":"algo-1","Timestamp":1682750992.500617}
{"Type":"cpu","Name":"cpu1","Dimension":"I/OWaitPercentage","Value":0.00,"NodeId":"algo-1","Timestamp":1682750992.500617}
{"Type":"cpu","Name":"cpu2","Dimension":"CPUUtilization","Value":96.00,"NodeId":"algo-1","Timestamp":1682750992.500617}
{"Type":"cpu","Name":"cpu2","Dimension":"I/OWaitPercentage","Value":4.00,"NodeId":"algo-1","Timestamp":1682750992.500617}
{"Type":"cpu","Name":"cpu0","Dimension":"CPUUtilization","Value":93.62,"NodeId":"algo-1","Timestamp":1682750992.500617}
{"Type":"cpu","Name":"cpu3","Dimension":"CPUUtilization","Value":100.00,"NodeId":"algo-1","Timestamp":1682750992.500617}
{"Type":"i/o","Name":"IOPS","Dimension":"","Value":4872.55,"NodeId":"algo-1","Timestamp":1682750992.500710}
{"Type":"i/o","Name":"ReadThroughputInBytesPerSecond","Dimension":"","Value":9041794.64,"NodeId":"algo-1","Timestamp":1682750992.500710}
{"Type":"i/o","Name":"WriteThroughputInBytesPerSecond","Dimension":"","Value":1154232560.73,"NodeId":"algo-1","Timestamp":1682750992.500710}
{"Type":"network","Name":"ReceiveBytesPerSecond","Dimension":"Algorithm","Value":0.00,"NodeId":"algo-1","Timestamp":1682750992.514454}
{"Type":"network","Name":"TransmitBytesPerSecond","Dimension":"Algorithm","Value":0.00,"NodeId":"algo-1","Timestamp":1682750992.514454}
{"Type":"network","Name":"TransmitBytesPerSecond","Dimension":"Platform","Value":581641.61,"NodeId":"algo-1","Timestamp":1682750992.514454}
{"Type":"network","Name":"ReceiveBytesPerSecond","Dimension":"Platform","Value":108017898.30,"NodeId":"algo-1","Timestamp":1682750992.514454}
{"Type":"memory","Name":"MemoryUsedPercent","Dimension":"","Value":12.59,"NodeId":"algo-1","Timestamp":1682750993.001236}
{"Type":"cpu","Name":"cpu3","Dimension":"I/OWaitPercentage","Value":11.76,"NodeId":"algo-1","Timestamp":1682750993.001325}
{"Type":"cpu","Name":"cpu0","Dimension":"I/OWaitPercentage","Value":8.00,"NodeId":"algo-1","Timestamp":1682750993.001325}
{"Type":"cpu","Name":"cpu1","Dimension":"CPUUtilization","Value":100.00,"NodeId":"algo-1","Timestamp":1682750993.001325}
{"Type":"cpu","Name":"cpu1","Dimension":"I/OWaitPercentage","Value":1.96,"NodeId":"algo-1","Timestamp":1682750993.001325}
{"Type":"cpu","Name":"cpu2","Dimension":"CPUUtilization","Value":93.88,"NodeId":"algo-1","Timestamp":1682750993.001325}
{"Type":"cpu","Name":"cpu2","Dimension":"I/OWaitPercentage","Value":6.12,"NodeId":"algo-1","Timestamp":1682750993.001325}
{"Type":"cpu","Name":"cpu0","Dimension":"CPUUtilization","Value":92.00,"NodeId":"algo-1","Timestamp":1682750993.001325}
{"Type":"cpu","Name":"cpu3","Dimension":"CPUUtilization","Value":100.00,"NodeId":"algo-1","Timestamp":1682750993.001325}
{"Type":"i/o","Name":"IOPS","Dimension":"","Value":577.21,"NodeId":"algo-1","Timestamp":1682750993.001398}
{"Type":"i/o","Name":"ReadThroughputInBytesPerSecond","Dimension":"","Value":0.00,"NodeId":"algo-1","Timestamp":1682750993.001398}
{"Type":"i/o","Name":"WriteThroughputInBytesPerSecond","Dimension":"","Value":132454331.54,"NodeId":"algo-1","Timestamp":1682750993.001398}
{"Type":"network","Name":"ReceiveBytesPerSecond","Dimension":"Algorithm","Value":0.00,"NodeId":"algo-1","Timestamp":1682750993.018113}
{"Type":"network","Name":"TransmitBytesPerSecond","Dimension":"Algorithm","Value":0.00,"NodeId":"algo-1","Timestamp":1682750993.018113}
{"Type":"network","Name":"ReceiveBytesPerSecond","Dimension":"Platform","Value":108530422.21,"NodeId":"algo-1","Timestamp":1682750993.018113}
{"Type":"network","Name":"TransmitBytesPerSecond","Dimension":"Platform","Value":446967.09,"NodeId":"algo-1","Timestamp":1682750993.018113}
{"Type":"memory","Name":"MemoryUsedPercent","Dimension":"","Value":12.84,"NodeId":"algo-1","Timestamp":1682750993.500513}
{"Type":"cpu","Name":"cpu3","Dimension":"I/OWaitPercentage","Value":6.12,"NodeId":"algo-1","Timestamp":1682750993.500605}
{"Type":"cpu","Name":"cpu0","Dimension":"I/OWaitPercentage","Value":4.35,"NodeId":"algo-1","Timestamp":1682750993.500605}
{"Type":"cpu","Name":"cpu1","Dimension":"CPUUtilization","Value":96.08,"NodeId":"algo-1","Timestamp":1682750993.500605}
{"Type":"cpu","Name":"cpu1","Dimension":"I/OWaitPercentage","Value":1.96,"NodeId":"algo-1","Timestamp":1682750993.500605}
{"Type":"cpu","Name":"cpu2","Dimension":"CPUUtilization","Value":96.00,"NodeId":"algo-1","Timestamp":1682750993.500605}
{"Type":"cpu","Name":"cpu2","Dimension":"I/OWaitPercentage","Value":8.00,"NodeId":"algo-1","Timestamp":1682750993.500605}
{"Type":"cpu","Name":"cpu0","Dimension":"CPUUtilization","Value":97.83,"NodeId":"algo-1","Timestamp":1682750993.500605}
{"Type":"cpu","Name":"cpu3","Dimension":"CPUUtilization","Value":100.00,"NodeId":"algo-1","Timestamp":1682750993.500605}
{"Type":"i/o","Name":"IOPS","Dimension":"","Value":4872.88,"NodeId":"algo-1","Timestamp":1682750993.500692}
{"Type":"i/o","Name":"ReadThroughputInBytesPerSecond","Dimension":"","Value":9042407.73,"NodeId":"algo-1","Timestamp":1682750993.500692}
{"Type":"i/o","Name":"WriteThroughputInBytesPerSecond","Dimension":"","Value":1154310825.40,"NodeId":"algo-1","Timestamp":1682750993.500692}
{"Type":"network","Name":"ReceiveBytesPerSecond","Dimension":"Algorithm","Value":0.00,"NodeId":"algo-1","Timestamp":1682750993.525757}
{"Type":"network","Name":"TransmitBytesPerSecond","Dimension":"Algorithm","Value":0.00,"NodeId":"algo-1","Timestamp":1682750993.525757}
{"Type":"network","Name":"ReceiveBytesPerSecond","Dimension":"Platform","Value":107890553.48,"NodeId":"algo-1","Timestamp":1682750993.525757}
{"Type":"network","Name":"TransmitBytesPerSecond","Dimension":"Platform","Value":460988.90,"NodeId":"algo-1","Timestamp":1682750993.525757}
{"Type":"memory","Name":"MemoryUsedPercent","Dimension":"","Value":13.09,"NodeId":"algo-1","Timestamp":1682750994.000877}
{"Type":"cpu","Name":"cpu3","Dimension":"I/OWaitPercentage","Value":19.57,"NodeId":"algo-1","Timestamp":1682750994.000956}
{"Type":"cpu","Name":"cpu0","Dimension":"I/OWaitPercentage","Value":10.20,"NodeId":"algo-1","Timestamp":1682750994.000956}
{"Type":"cpu","Name":"cpu1","Dimension":"CPUUtilization","Value":95.65,"NodeId":"algo-1","Timestamp":1682750994.000956}
{"Type":"cpu","Name":"cpu1","Dimension":"I/OWaitPercentage","Value":26.09,"NodeId":"algo-1","Timestamp":1682750994.000956}
{"Type":"cpu","Name":"cpu2","Dimension":"CPUUtilization","Value":88.00,"NodeId":"algo-1","Timestamp":1682750994.000956}
{"Type":"cpu","Name":"cpu2","Dimension":"I/OWaitPercentage","Value":16.00,"NodeId":"algo-1","Timestamp":1682750994.000956}
{"Type":"cpu","Name":"cpu0","Dimension":"CPUUtilization","Value":95.92,"NodeId":"algo-1","Timestamp":1682750994.000956}
{"Type":"cpu","Name":"cpu3","Dimension":"CPUUtilization","Value":91.30,"NodeId":"algo-1","Timestamp":1682750994.000956}
{"Type":"i/o","Name":"IOPS","Dimension":"","Value":577.60,"NodeId":"algo-1","Timestamp":1682750994.001040}
{"Type":"i/o","Name":"ReadThroughputInBytesPerSecond","Dimension":"","Value":0.00,"NodeId":"algo-1","Timestamp":1682750994.001040}
{"Type":"i/o","Name":"WriteThroughputInBytesPerSecond","Dimension":"","Value":132544270.63,"NodeId":"algo-1","Timestamp":1682750994.001040}
{"Type":"network","Name":"ReceiveBytesPerSecond","Dimension":"Algorithm","Value":0.00,"NodeId":"algo-1","Timestamp":1682750994.005615}
{"Type":"network","Name":"TransmitBytesPerSecond","Dimension":"Platform","Value":739259.38,"NodeId":"algo-1","Timestamp":1682750994.005615}
{"Type":"network","Name":"ReceiveBytesPerSecond","Dimension":"Platform","Value":114642429.61,"NodeId":"algo-1","Timestamp":1682750994.005615}
{"Type":"network","Name":"TransmitBytesPerSecond","Dimension":"Algorithm","Value":0.00,"NodeId":"algo-1","Timestamp":1682750994.005615}
{"Type":"memory","Name":"MemoryUsedPercent","Dimension":"","Value":13.49,"NodeId":"algo-1","Timestamp":1682750994.500552}
{"Type":"cpu","Name":"cpu3","Dimension":"I/OWaitPercentage","Value":10.00,"NodeId":"algo-1","Timestamp":1682750994.500632}
{"Type":"cpu","Name":"cpu0","Dimension":"I/OWaitPercentage","Value":2.00,"NodeId":"algo-1","Timestamp":1682750994.500632}
{"Type":"cpu","Name":"cpu1","Dimension":"CPUUtilization","Value":95.74,"NodeId":"algo-1","Timestamp":1682750994.500632}
{"Type":"cpu","Name":"cpu1","Dimension":"I/OWaitPercentage","Value":17.02,"NodeId":"algo-1","Timestamp":1682750994.500632}
{"Type":"cpu","Name":"cpu2","Dimension":"CPUUtilization","Value":91.49,"NodeId":"algo-1","Timestamp":1682750994.500632}
{"Type":"cpu","Name":"cpu2","Dimension":"I/OWaitPercentage","Value":8.51,"NodeId":"algo-1","Timestamp":1682750994.500632}
{"Type":"cpu","Name":"cpu0","Dimension":"CPUUtilization","Value":94.00,"NodeId":"algo-1","Timestamp":1682750994.500632}
{"Type":"cpu","Name":"cpu3","Dimension":"CPUUtilization","Value":96.00,"NodeId":"algo-1","Timestamp":1682750994.500632}
{"Type":"i/o","Name":"IOPS","Dimension":"","Value":4869.10,"NodeId":"algo-1","Timestamp":1682750994.500721}
{"Type":"i/o","Name":"ReadThroughputInBytesPerSecond","Dimension":"","Value":9035392.35,"NodeId":"algo-1","Timestamp":1682750994.500721}
{"Type":"i/o","Name":"WriteThroughputInBytesPerSecond","Dimension":"","Value":1153415274.32,"NodeId":"algo-1","Timestamp":1682750994.500721}
{"Type":"network","Name":"ReceiveBytesPerSecond","Dimension":"Algorithm","Value":0.00,"NodeId":"algo-1","Timestamp":1682750994.505669}
{"Type":"network","Name":"TransmitBytesPerSecond","Dimension":"Algorithm","Value":0.00,"NodeId":"algo-1","Timestamp":1682750994.505669}
{"Type":"network","Name":"TransmitBytesPerSecond","Dimension":"Platform","Value":579616.09,"NodeId":"algo-1","Timestamp":1682750994.505669}
{"Type":"network","Name":"ReceiveBytesPerSecond","Dimension":"Platform","Value":109728667.71,"NodeId":"algo-1","Timestamp":1682750994.505669}
{"Type":"memory","Name":"MemoryUsedPercent","Dimension":"","Value":13.78,"NodeId":"algo-1","Timestamp":1682750995.000575}
{"Type":"i/o","Name":"IOPS","Dimension":"","Value":578.08,"NodeId":"algo-1","Timestamp":1682750995.000654}
{"Type":"i/o","Name":"ReadThroughputInBytesPerSecond","Dimension":"","Value":0.00,"NodeId":"algo-1","Timestamp":1682750995.000654}
{"Type":"i/o","Name":"WriteThroughputInBytesPerSecond","Dimension":"","Value":132654636.32,"NodeId":"algo-1","Timestamp":1682750995.000654}
{"Type":"cpu","Name":"cpu0","Dimension":"CPUUtilization","Value":98.04,"NodeId":"algo-1","Timestamp":1682750995.000748}
{"Type":"cpu","Name":"cpu0","Dimension":"I/OWaitPercentage","Value":0.00,"NodeId":"algo-1","Timestamp":1682750995.000748}
{"Type":"cpu","Name":"cpu1","Dimension":"CPUUtilization","Value":97.96,"NodeId":"algo-1","Timestamp":1682750995.000748}
{"Type":"cpu","Name":"cpu1","Dimension":"I/OWaitPercentage","Value":2.04,"NodeId":"algo-1","Timestamp":1682750995.000748}
{"Type":"cpu","Name":"cpu2","Dimension":"CPUUtilization","Value":100.00,"NodeId":"algo-1","Timestamp":1682750995.000748}
{"Type":"cpu","Name":"cpu2","Dimension":"I/OWaitPercentage","Value":2.08,"NodeId":"algo-1","Timestamp":1682750995.000748}
{"Type":"cpu","Name":"cpu3","Dimension":"CPUUtilization","Value":100.00,"NodeId":"algo-1","Timestamp":1682750995.000748}
{"Type":"cpu","Name":"cpu3","Dimension":"I/OWaitPercentage","Value":4.17,"NodeId":"algo-1","Timestamp":1682750995.000748}
{"Type":"network","Name":"TransmitBytesPerSecond","Dimension":"Platform","Value":250221.57,"NodeId":"algo-1","Timestamp":1682750995.020109}
{"Type":"network","Name":"ReceiveBytesPerSecond","Dimension":"Algorithm","Value":0.00,"NodeId":"algo-1","Timestamp":1682750995.020109}
{"Type":"network","Name":"ReceiveBytesPerSecond","Dimension":"Platform","Value":91039523.69,"NodeId":"algo-1","Timestamp":1682750995.020109}
{"Type":"network","Name":"TransmitBytesPerSecond","Dimension":"Algorithm","Value":0.00,"NodeId":"algo-1","Timestamp":1682750995.020109}
{"Type":"i/o","Name":"WriteThroughputInBytesPerSecond","Dimension":"","Value":1152993316.33,"NodeId":"algo-1","Timestamp":1682750995.500518}
{"Type":"i/o","Name":"ReadThroughputInBytesPerSecond","Dimension":"","Value":9032086.90,"NodeId":"algo-1","Timestamp":1682750995.500518}
{"Type":"i/o","Name":"IOPS","Dimension":"","Value":4867.32,"NodeId":"algo-1","Timestamp":1682750995.500518}
{"Type":"cpu","Name":"cpu0","Dimension":"CPUUtilization","Value":95.83,"NodeId":"algo-1","Timestamp":1682750995.500636}
{"Type":"cpu","Name":"cpu2","Dimension":"CPUUtilization","Value":94.00,"NodeId":"algo-1","Timestamp":1682750995.500636}
{"Type":"cpu","Name":"cpu2","Dimension":"I/OWaitPercentage","Value":26.00,"NodeId":"algo-1","Timestamp":1682750995.500636}
{"Type":"cpu","Name":"cpu3","Dimension":"CPUUtilization","Value":92.16,"NodeId":"algo-1","Timestamp":1682750995.500636}
{"Type":"cpu","Name":"cpu3","Dimension":"I/OWaitPercentage","Value":11.76,"NodeId":"algo-1","Timestamp":1682750995.500636}
{"Type":"cpu","Name":"cpu1","Dimension":"I/OWaitPercentage","Value":8.00,"NodeId":"algo-1","Timestamp":1682750995.500636}
{"Type":"cpu","Name":"cpu1","Dimension":"CPUUtilization","Value":92.00,"NodeId":"algo-1","Timestamp":1682750995.500636}
{"Type":"cpu","Name":"cpu0","Dimension":"I/OWaitPercentage","Value":8.33,"NodeId":"algo-1","Timestamp":1682750995.500636}
{"Type":"memory","Name":"MemoryUsedPercent","Dimension":"","Value":14.10,"NodeId":"algo-1","Timestamp":1682750995.501081}
{"Type":"network","Name":"TransmitBytesPerSecond","Dimension":"Platform","Value":574171.40,"NodeId":"algo-1","Timestamp":1682750995.503992}
{"Type":"network","Name":"ReceiveBytesPerSecond","Dimension":"Platform","Value":112227644.40,"NodeId":"algo-1","Timestamp":1682750995.503992}
{"Type":"network","Name":"TransmitBytesPerSecond","Dimension":"Algorithm","Value":0.00,"NodeId":"algo-1","Timestamp":1682750995.503992}
{"Type":"network","Name":"ReceiveBytesPerSecond","Dimension":"Algorithm","Value":0.00,"NodeId":"algo-1","Timestamp":1682750995.503992}
{"Type":"memory","Name":"MemoryUsedPercent","Dimension":"","Value":14.36,"NodeId":"algo-1","Timestamp":1682750996.001721}
{"Type":"cpu","Name":"cpu1","Dimension":"I/OWaitPercentage","Value":20.75,"NodeId":"algo-1","Timestamp":1682750996.001830}
{"Type":"cpu","Name":"cpu0","Dimension":"CPUUtilization","Value":90.20,"NodeId":"algo-1","Timestamp":1682750996.001830}
{"Type":"cpu","Name":"cpu0","Dimension":"I/OWaitPercentage","Value":9.80,"NodeId":"algo-1","Timestamp":1682750996.001830}
{"Type":"cpu","Name":"cpu2","Dimension":"I/OWaitPercentage","Value":12.24,"NodeId":"algo-1","Timestamp":1682750996.001830}
{"Type":"cpu","Name":"cpu3","Dimension":"CPUUtilization","Value":95.83,"NodeId":"algo-1","Timestamp":1682750996.001830}
{"Type":"cpu","Name":"cpu3","Dimension":"I/OWaitPercentage","Value":41.67,"NodeId":"algo-1","Timestamp":1682750996.001830}
{"Type":"cpu","Name":"cpu1","Dimension":"CPUUtilization","Value":81.13,"NodeId":"algo-1","Timestamp":1682750996.001830}
{"Type":"cpu","Name":"cpu2","Dimension":"CPUUtilization","Value":91.84,"NodeId":"algo-1","Timestamp":1682750996.001830}
{"Type":"i/o","Name":"WriteThroughputInBytesPerSecond","Dimension":"","Value":132264252.45,"NodeId":"algo-1","Timestamp":1682750996.001926}
{"Type":"i/o","Name":"ReadThroughputInBytesPerSecond","Dimension":"","Value":0.00,"NodeId":"algo-1","Timestamp":1682750996.001926}
{"Type":"i/o","Name":"IOPS","Dimension":"","Value":576.38,"NodeId":"algo-1","Timestamp":1682750996.001926}
{"Type":"network","Name":"ReceiveBytesPerSecond","Dimension":"Algorithm","Value":0.00,"NodeId":"algo-1","Timestamp":1682750996.013977}
{"Type":"network","Name":"TransmitBytesPerSecond","Dimension":"Algorithm","Value":0.00,"NodeId":"algo-1","Timestamp":1682750996.013977}
{"Type":"network","Name":"ReceiveBytesPerSecond","Dimension":"Platform","Value":108107801.23,"NodeId":"algo-1","Timestamp":1682750996.013977}
{"Type":"network","Name":"TransmitBytesPerSecond","Dimension":"Platform","Value":688044.13,"NodeId":"algo-1","Timestamp":1682750996.013977}
{"Type":"memory","Name":"MemoryUsedPercent","Dimension":"","Value":14.45,"NodeId":"algo-1","Timestamp":1682750996.500640}
{"Type":"cpu","Name":"cpu1","Dimension":"CPUUtilization","Value":97.92,"NodeId":"algo-1","Timestamp":1682750996.500794}
{"Type":"cpu","Name":"cpu0","Dimension":"I/OWaitPercentage","Value":6.25,"NodeId":"algo-1","Timestamp":1682750996.500794}
{"Type":"cpu","Name":"cpu0","Dimension":"CPUUtilization","Value":95.83,"NodeId":"algo-1","Timestamp":1682750996.500794}
{"Type":"cpu","Name":"cpu1","Dimension":"I/OWaitPercentage","Value":6.25,"NodeId":"algo-1","Timestamp":1682750996.500794}
{"Type":"cpu","Name":"cpu2","Dimension":"CPUUtilization","Value":88.00,"NodeId":"algo-1","Timestamp":1682750996.500794}
{"Type":"cpu","Name":"cpu2","Dimension":"I/OWaitPercentage","Value":6.00,"NodeId":"algo-1","Timestamp":1682750996.500794}
{"Type":"cpu","Name":"cpu3","Dimension":"CPUUtilization","Value":100.00,"NodeId":"algo-1","Timestamp":1682750996.500794}
{"Type":"cpu","Name":"cpu3","Dimension":"I/OWaitPercentage","Value":17.02,"NodeId":"algo-1","Timestamp":1682750996.500794}
{"Type":"i/o","Name":"IOPS","Dimension":"","Value":4875.42,"NodeId":"algo-1","Timestamp":1682750996.500959}
{"Type":"i/o","Name":"ReadThroughputInBytesPerSecond","Dimension":"","Value":9047116.65,"NodeId":"algo-1","Timestamp":1682750996.500959}
{"Type":"i/o","Name":"WriteThroughputInBytesPerSecond","Dimension":"","Value":1154911943.08,"NodeId":"algo-1","Timestamp":1682750996.500959}
{"Type":"network","Name":"ReceiveBytesPerSecond","Dimension":"Algorithm","Value":0.00,"NodeId":"algo-1","Timestamp":1682750996.522940}
{"Type":"network","Name":"TransmitBytesPerSecond","Dimension":"Algorithm","Value":0.00,"NodeId":"algo-1","Timestamp":1682750996.522940}
{"Type":"network","Name":"ReceiveBytesPerSecond","Dimension":"Platform","Value":107541239.77,"NodeId":"algo-1","Timestamp":1682750996.522940}
{"Type":"network","Name":"TransmitBytesPerSecond","Dimension":"Platform","Value":476687.03,"NodeId":"algo-1","Timestamp":1682750996.522940}
{"Type":"memory","Name":"MemoryUsedPercent","Dimension":"","Value":14.89,"NodeId":"algo-1","Timestamp":1682750997.002509}
{"Type":"cpu","Name":"cpu1","Dimension":"CPUUtilization","Value":100.00,"NodeId":"algo-1","Timestamp":1682750997.002587}
{"Type":"cpu","Name":"cpu0","Dimension":"I/OWaitPercentage","Value":4.00,"NodeId":"algo-1","Timestamp":1682750997.002587}
{"Type":"cpu","Name":"cpu0","Dimension":"CPUUtilization","Value":98.00,"NodeId":"algo-1","Timestamp":1682750997.002587}
{"Type":"cpu","Name":"cpu1","Dimension":"I/OWaitPercentage","Value":4.08,"NodeId":"algo-1","Timestamp":1682750997.002587}
{"Type":"cpu","Name":"cpu2","Dimension":"CPUUtilization","Value":93.88,"NodeId":"algo-1","Timestamp":1682750997.002587}
{"Type":"cpu","Name":"cpu2","Dimension":"I/OWaitPercentage","Value":4.08,"NodeId":"algo-1","Timestamp":1682750997.002587}
{"Type":"cpu","Name":"cpu3","Dimension":"CPUUtilization","Value":100.00,"NodeId":"algo-1","Timestamp":1682750997.002587}
{"Type":"cpu","Name":"cpu3","Dimension":"I/OWaitPercentage","Value":4.08,"NodeId":"algo-1","Timestamp":1682750997.002587}
{"Type":"i/o","Name":"IOPS","Dimension":"","Value":576.03,"NodeId":"algo-1","Timestamp":1682750997.002669}
{"Type":"i/o","Name":"WriteThroughputInBytesPerSecond","Dimension":"","Value":132184742.62,"NodeId":"algo-1","Timestamp":1682750997.002669}
{"Type":"i/o","Name":"ReadThroughputInBytesPerSecond","Dimension":"","Value":0.00,"NodeId":"algo-1","Timestamp":1682750997.002669}
{"Type":"network","Name":"ReceiveBytesPerSecond","Dimension":"Algorithm","Value":0.00,"NodeId":"algo-1","Timestamp":1682750997.007113}
{"Type":"network","Name":"TransmitBytesPerSecond","Dimension":"Algorithm","Value":0.00,"NodeId":"algo-1","Timestamp":1682750997.007113}
{"Type":"network","Name":"ReceiveBytesPerSecond","Dimension":"Platform","Value":109005957.60,"NodeId":"algo-1","Timestamp":1682750997.007113}
{"Type":"network","Name":"TransmitBytesPerSecond","Dimension":"Platform","Value":215105.01,"NodeId":"algo-1","Timestamp":1682750997.007113}
{"Type":"memory","Name":"MemoryUsedPercent","Dimension":"","Value":15.00,"NodeId":"algo-1","Timestamp":1682750997.503185}
{"Type":"cpu","Name":"cpu1","Dimension":"CPUUtilization","Value":98.08,"NodeId":"algo-1","Timestamp":1682750997.503260}
{"Type":"cpu","Name":"cpu0","Dimension":"I/OWaitPercentage","Value":4.00,"NodeId":"algo-1","Timestamp":1682750997.503260}
{"Type":"cpu","Name":"cpu0","Dimension":"CPUUtilization","Value":100.00,"NodeId":"algo-1","Timestamp":1682750997.503260}
{"Type":"cpu","Name":"cpu1","Dimension":"I/OWaitPercentage","Value":1.92,"NodeId":"algo-1","Timestamp":1682750997.503260}
{"Type":"cpu","Name":"cpu2","Dimension":"CPUUtilization","Value":97.92,"NodeId":"algo-1","Timestamp":1682750997.503260}
{"Type":"cpu","Name":"cpu2","Dimension":"I/OWaitPercentage","Value":4.17,"NodeId":"algo-1","Timestamp":1682750997.503260}
{"Type":"cpu","Name":"cpu3","Dimension":"CPUUtilization","Value":96.15,"NodeId":"algo-1","Timestamp":1682750997.503260}
{"Type":"cpu","Name":"cpu3","Dimension":"I/OWaitPercentage","Value":5.77,"NodeId":"algo-1","Timestamp":1682750997.503260}
{"Type":"i/o","Name":"IOPS","Dimension":"","Value":4859.40,"NodeId":"algo-1","Timestamp":1682750997.503348}
{"Type":"i/o","Name":"WriteThroughputInBytesPerSecond","Dimension":"","Value":1151117230.60,"NodeId":"algo-1","Timestamp":1682750997.503348}
{"Type":"i/o","Name":"ReadThroughputInBytesPerSecond","Dimension":"","Value":9017390.39,"NodeId":"algo-1","Timestamp":1682750997.503348}
{"Type":"network","Name":"ReceiveBytesPerSecond","Dimension":"Algorithm","Value":0.00,"NodeId":"algo-1","Timestamp":1682750997.514166}
{"Type":"network","Name":"TransmitBytesPerSecond","Dimension":"Algorithm","Value":0.00,"NodeId":"algo-1","Timestamp":1682750997.514166}
{"Type":"network","Name":"ReceiveBytesPerSecond","Dimension":"Platform","Value":102170391.78,"NodeId":"algo-1","Timestamp":1682750997.514166}
{"Type":"network","Name":"TransmitBytesPerSecond","Dimension":"Platform","Value":246409.96,"NodeId":"algo-1","Timestamp":1682750997.514166}
{"Type":"memory","Name":"MemoryUsedPercent","Dimension":"","Value":15.03,"NodeId":"algo-1","Timestamp":1682750998.000555}
{"Type":"cpu","Name":"cpu3","Dimension":"CPUUtilization","Value":100.00,"NodeId":"algo-1","Timestamp":1682750998.000636}
{"Type":"cpu","Name":"cpu0","Dimension":"I/OWaitPercentage","Value":2.04,"NodeId":"algo-1","Timestamp":1682750998.000636}
{"Type":"cpu","Name":"cpu1","Dimension":"CPUUtilization","Value":100.00,"NodeId":"algo-1","Timestamp":1682750998.000636}
{"Type":"cpu","Name":"cpu1","Dimension":"I/OWaitPercentage","Value":0.00,"NodeId":"algo-1","Timestamp":1682750998.000636}
{"Type":"cpu","Name":"cpu2","Dimension":"CPUUtilization","Value":98.00,"NodeId":"algo-1","Timestamp":1682750998.000636}
{"Type":"cpu","Name":"cpu3","Dimension":"I/OWaitPercentage","Value":0.00,"NodeId":"algo-1","Timestamp":1682750998.000636}
{"Type":"cpu","Name":"cpu0","Dimension":"CPUUtilization","Value":97.96,"NodeId":"algo-1","Timestamp":1682750998.000636}
{"Type":"cpu","Name":"cpu2","Dimension":"I/OWaitPercentage","Value":12.00,"NodeId":"algo-1","Timestamp":1682750998.000636}
{"Type":"i/o","Name":"IOPS","Dimension":"","Value":585.04,"NodeId":"algo-1","Timestamp":1682750998.000747}
{"Type":"i/o","Name":"ReadThroughputInBytesPerSecond","Dimension":"","Value":0.00,"NodeId":"algo-1","Timestamp":1682750998.000747}
{"Type":"i/o","Name":"WriteThroughputInBytesPerSecond","Dimension":"","Value":133354871.99,"NodeId":"algo-1","Timestamp":1682750998.000747}
{"Type":"network","Name":"ReceiveBytesPerSecond","Dimension":"Algorithm","Value":0.00,"NodeId":"algo-1","Timestamp":1682750998.008628}
{"Type":"network","Name":"TransmitBytesPerSecond","Dimension":"Algorithm","Value":0.00,"NodeId":"algo-1","Timestamp":1682750998.008628}
{"Type":"network","Name":"ReceiveBytesPerSecond","Dimension":"Platform","Value":101914264.89,"NodeId":"algo-1","Timestamp":1682750998.008628}
{"Type":"network","Name":"TransmitBytesPerSecond","Dimension":"Platform","Value":160129.75,"NodeId":"algo-1","Timestamp":1682750998.008628}
{"Type":"memory","Name":"MemoryUsedPercent","Dimension":"","Value":15.15,"NodeId":"algo-1","Timestamp":1682750998.501247}
{"Type":"cpu","Name":"cpu3","Dimension":"I/OWaitPercentage","Value":14.00,"NodeId":"algo-1","Timestamp":1682750998.501345}
{"Type":"cpu","Name":"cpu0","Dimension":"I/OWaitPercentage","Value":11.11,"NodeId":"algo-1","Timestamp":1682750998.501345}
{"Type":"cpu","Name":"cpu1","Dimension":"CPUUtilization","Value":92.00,"NodeId":"algo-1","Timestamp":1682750998.501345}
{"Type":"cpu","Name":"cpu0","Dimension":"CPUUtilization","Value":98.15,"NodeId":"algo-1","Timestamp":1682750998.501345}
{"Type":"cpu","Name":"cpu2","Dimension":"CPUUtilization","Value":87.76,"NodeId":"algo-1","Timestamp":1682750998.501345}
{"Type":"cpu","Name":"cpu2","Dimension":"I/OWaitPercentage","Value":18.37,"NodeId":"algo-1","Timestamp":1682750998.501345}
{"Type":"cpu","Name":"cpu3","Dimension":"CPUUtilization","Value":88.00,"NodeId":"algo-1","Timestamp":1682750998.501345}
{"Type":"cpu","Name":"cpu1","Dimension":"I/OWaitPercentage","Value":6.00,"NodeId":"algo-1","Timestamp":1682750998.501345}
{"Type":"i/o","Name":"IOPS","Dimension":"","Value":4859.30,"NodeId":"algo-1","Timestamp":1682750998.501436}
{"Type":"i/o","Name":"ReadThroughputInBytesPerSecond","Dimension":"","Value":9017205.75,"NodeId":"algo-1","Timestamp":1682750998.501436}
{"Type":"i/o","Name":"WriteThroughputInBytesPerSecond","Dimension":"","Value":1151093660.58,"NodeId":"algo-1","Timestamp":1682750998.501436}
{"Type":"network","Name":"ReceiveBytesPerSecond","Dimension":"Algorithm","Value":0.00,"NodeId":"algo-1","Timestamp":1682750998.509758}
{"Type":"network","Name":"TransmitBytesPerSecond","Dimension":"Algorithm","Value":0.00,"NodeId":"algo-1","Timestamp":1682750998.509758}
{"Type":"network","Name":"ReceiveBytesPerSecond","Dimension":"Platform","Value":109852263.02,"NodeId":"algo-1","Timestamp":1682750998.509758}
{"Type":"network","Name":"TransmitBytesPerSecond","Dimension":"Platform","Value":707255.46,"NodeId":"algo-1","Timestamp":1682750998.509758}
{"Type":"memory","Name":"MemoryUsedPercent","Dimension":"","Value":15.43,"NodeId":"algo-1","Timestamp":1682750999.005252}
{"Type":"i/o","Name":"WriteThroughputInBytesPerSecond","Dimension":"","Value":131636976.90,"NodeId":"algo-1","Timestamp":1682750999.005327}
{"Type":"i/o","Name":"ReadThroughputInBytesPerSecond","Dimension":"","Value":0.00,"NodeId":"algo-1","Timestamp":1682750999.005327}
{"Type":"i/o","Name":"IOPS","Dimension":"","Value":577.51,"NodeId":"algo-1","Timestamp":1682750999.005327}
{"Type":"cpu","Name":"cpu0","Dimension":"CPUUtilization","Value":89.58,"NodeId":"algo-1","Timestamp":1682750999.005419}
{"Type":"cpu","Name":"cpu1","Dimension":"CPUUtilization","Value":91.67,"NodeId":"algo-1","Timestamp":1682750999.005419}
{"Type":"cpu","Name":"cpu1","Dimension":"I/OWaitPercentage","Value":20.83,"NodeId":"algo-1","Timestamp":1682750999.005419}
{"Type":"cpu","Name":"cpu2","Dimension":"CPUUtilization","Value":79.59,"NodeId":"algo-1","Timestamp":1682750999.005419}
{"Type":"cpu","Name":"cpu2","Dimension":"I/OWaitPercentage","Value":12.24,"NodeId":"algo-1","Timestamp":1682750999.005419}
{"Type":"cpu","Name":"cpu3","Dimension":"CPUUtilization","Value":90.20,"NodeId":"algo-1","Timestamp":1682750999.005419}
{"Type":"cpu","Name":"cpu3","Dimension":"I/OWaitPercentage","Value":19.61,"NodeId":"algo-1","Timestamp":1682750999.005419}
{"Type":"cpu","Name":"cpu0","Dimension":"I/OWaitPercentage","Value":12.50,"NodeId":"algo-1","Timestamp":1682750999.005419}
{"Type":"network","Name":"TransmitBytesPerSecond","Dimension":"Algorithm","Value":0.00,"NodeId":"algo-1","Timestamp":1682750999.018162}
{"Type":"network","Name":"ReceiveBytesPerSecond","Dimension":"Platform","Value":108991644.92,"NodeId":"algo-1","Timestamp":1682750999.018162}
{"Type":"network","Name":"TransmitBytesPerSecond","Dimension":"Platform","Value":698148.50,"NodeId":"algo-1","Timestamp":1682750999.018162}
{"Type":"network","Name":"ReceiveBytesPerSecond","Dimension":"Algorithm","Value":0.00,"NodeId":"algo-1","Timestamp":1682750999.018162}
{"Type":"memory","Name":"MemoryUsedPercent","Dimension":"","Value":15.48,"NodeId":"algo-1","Timestamp":1682750999.500527}
{"Type":"cpu","Name":"cpu3","Dimension":"CPUUtilization","Value":100.00,"NodeId":"algo-1","Timestamp":1682750999.500609}
{"Type":"cpu","Name":"cpu0","Dimension":"CPUUtilization","Value":97.92,"NodeId":"algo-1","Timestamp":1682750999.500609}
{"Type":"cpu","Name":"cpu0","Dimension":"I/OWaitPercentage","Value":2.08,"NodeId":"algo-1","Timestamp":1682750999.500609}
{"Type":"cpu","Name":"cpu3","Dimension":"I/OWaitPercentage","Value":6.00,"NodeId":"algo-1","Timestamp":1682750999.500609}
{"Type":"cpu","Name":"cpu1","Dimension":"I/OWaitPercentage","Value":2.08,"NodeId":"algo-1","Timestamp":1682750999.500609}
{"Type":"cpu","Name":"cpu2","Dimension":"CPUUtilization","Value":92.00,"NodeId":"algo-1","Timestamp":1682750999.500609}
{"Type":"cpu","Name":"cpu2","Dimension":"I/OWaitPercentage","Value":6.00,"NodeId":"algo-1","Timestamp":1682750999.500609}
{"Type":"cpu","Name":"cpu1","Dimension":"CPUUtilization","Value":97.92,"NodeId":"algo-1","Timestamp":1682750999.500609}
{"Type":"i/o","Name":"IOPS","Dimension":"","Value":4911.27,"NodeId":"algo-1","Timestamp":1682750999.500718}
{"Type":"i/o","Name":"ReadThroughputInBytesPerSecond","Dimension":"","Value":9113639.15,"NodeId":"algo-1","Timestamp":1682750999.500718}
{"Type":"i/o","Name":"WriteThroughputInBytesPerSecond","Dimension":"","Value":1163403889.53,"NodeId":"algo-1","Timestamp":1682750999.500718}
{"Type":"network","Name":"ReceiveBytesPerSecond","Dimension":"Algorithm","Value":0.00,"NodeId":"algo-1","Timestamp":1682750999.510632}
{"Type":"network","Name":"TransmitBytesPerSecond","Dimension":"Algorithm","Value":0.00,"NodeId":"algo-1","Timestamp":1682750999.510632}
{"Type":"network","Name":"ReceiveBytesPerSecond","Dimension":"Platform","Value":109972578.63,"NodeId":"algo-1","Timestamp":1682750999.510632}
{"Type":"network","Name":"TransmitBytesPerSecond","Dimension":"Platform","Value":253386.35,"NodeId":"algo-1","Timestamp":1682750999.510632}
